<?xml version="1.0"?>
<ruleset name="Headless Converter Plugin Ruleset">
	<file>.</file>
	<arg name="extensions" value="php"/>
	<arg value="-colors"/>
	<arg value="ns"/>
	<exclude-pattern>vendor</exclude-pattern>
	<exclude-pattern>tests</exclude-pattern>
	<rule ref="WordPress">
		<exclude name="PSR12.Files.FileHeader.IncorrectOrder" />
		<exclude name="Squiz.Commenting.FileComment.Missing" />
		<exclude name="Squiz.Commenting.FileComment.MissingPackageTag" />
		<exclude name="WordPress.Files.FileName.NotHyphenatedLowercase" />
		<exclude name="WordPress.Files.FileName.InvalidClassFileName" />
		<exclude name="WordPress.PHP.YodaConditions.NotYoda" />
	</rule>
</ruleset>